envguardx/__init__.py
envguardx/checker.py
envguardx/cli.py
envguardx/utils.py
envguardx-0.2.0.dist-info/METADATA
envguardx-0.2.0.dist-info/WHEEL
envguardx-0.2.0.dist-info/entry_points.txt
envguardx-0.2.0.dist-info/top_level.txt
envguardx-0.2.0.dist-info/RECORD
