Metadata-Version: 2.4
Name: envguardx
Version: 0.2.0
Summary: CLI tool to validate .env files for safety and completeness
Author: Moses Sapele
Requires-Python: >=3.8
Requires-Dist: click>=8.1.0
Requires-Dist: python-dotenv>=1.0.0
